<?xml version="1.0" encoding="utf-8" ?>
<dwsync>
<file name="check_login.php" server="184.106.111.74" local="129390273000000000" remote="129390273000000000" />
<file name="check_admin.php" server="184.106.111.74" local="129390273000000000" remote="129390273000000000" />
<file name="cloudfiles.php" server="184.106.111.74" local="129390459000000000" remote="129390459000000000" />
<file name="cloudfiles_exceptions.php" server="184.106.111.74" local="129390459600000000" remote="129390459600000000" />
<file name="cloudfiles_http.php" server="184.106.111.74" local="129390460200000000" remote="129390460200000000" />
<file name="image_resize.php" server="184.106.111.74" local="129390273000000000" remote="129390273000000000" />
<file name="index.php" server="184.106.111.74" local="129390273000000000" remote="129390273000000000" />
<file name="misc.php" server="184.106.111.74" local="129390273000000000" remote="129390273000000000" />
<file name="postmark.php" server="184.106.111.74" local="129390273000000000" remote="129390273000000000" />
<file name="rating.php" server="184.106.111.74" local="129390273000000000" remote="129390273000000000" />
<file name="recaptchalib.php" server="184.106.111.74" local="129390273000000000" remote="129390273000000000" />
<file name="settings.php" server="184.106.111.74" local="129396402600000000" remote="129396402600000000" />
<file name="sql_sanitize.php" server="184.106.111.74" local="129390273000000000" remote="129390273000000000" />
<file name="watermark.png" server="184.106.111.74" local="129390273000000000" remote="129390273000000000" />
<file name="get_filelist.php" server="184.106.111.74" local="129416797359307070" remote="129417085200000000" />
</dwsync>